{
	"cmake" : 
	{
		"generator" : 
		{
			"multiConfig" : false,
			"name" : "Unix Makefiles"
		},
		"paths" : 
		{
			"cmake" : "/usr/bin/cmake",
			"cpack" : "/usr/bin/cpack",
			"ctest" : "/usr/bin/ctest",
			"root" : "/usr/share/cmake-3.31"
		},
		"version" : 
		{
			"isDirty" : false,
			"major" : 3,
			"minor" : 31,
			"patch" : 6,
			"string" : "3.31.6",
			"suffix" : ""
		}
	},
	"objects" : 
	[
		{
			"jsonFile" : "codemodel-v2-8f6206b0adbd7e94cc30.json",
			"kind" : "codemodel",
			"version" : 
			{
				"major" : 2,
				"minor" : 7
			}
		},
		{
			"jsonFile" : "configureLog-v1-4ffc90877c1a95b601cf.json",
			"kind" : "configureLog",
			"version" : 
			{
				"major" : 1,
				"minor" : 0
			}
		},
		{
			"jsonFile" : "cache-v2-e0ccb5427f646b3d14aa.json",
			"kind" : "cache",
			"version" : 
			{
				"major" : 2,
				"minor" : 0
			}
		},
		{
			"jsonFile" : "cmakeFiles-v1-974a3d65760ee1985557.json",
			"kind" : "cmakeFiles",
			"version" : 
			{
				"major" : 1,
				"minor" : 1
			}
		},
		{
			"jsonFile" : "toolchains-v1-1ad29d7dad0522fb55c2.json",
			"kind" : "toolchains",
			"version" : 
			{
				"major" : 1,
				"minor" : 0
			}
		}
	],
	"reply" : 
	{
		"client-neocmake" : 
		{
			"query.json" : 
			{
				"requests" : 
				[
					{
						"kind" : "codemodel",
						"version" : 
						[
							{
								"major" : 2,
								"minor" : 7
							}
						]
					},
					{
						"kind" : "configureLog",
						"version" : 
						[
							{
								"major" : 1,
								"minor" : 0
							}
						]
					},
					{
						"kind" : "cache",
						"version" : 
						[
							{
								"major" : 2,
								"minor" : 0
							}
						]
					},
					{
						"kind" : "cmakeFiles",
						"version" : 
						[
							{
								"major" : 1,
								"minor" : 1
							}
						]
					},
					{
						"kind" : "toolchains",
						"version" : 
						[
							{
								"major" : 1,
								"minor" : 0
							}
						]
					}
				],
				"responses" : 
				[
					{
						"jsonFile" : "codemodel-v2-8f6206b0adbd7e94cc30.json",
						"kind" : "codemodel",
						"version" : 
						{
							"major" : 2,
							"minor" : 7
						}
					},
					{
						"jsonFile" : "configureLog-v1-4ffc90877c1a95b601cf.json",
						"kind" : "configureLog",
						"version" : 
						{
							"major" : 1,
							"minor" : 0
						}
					},
					{
						"jsonFile" : "cache-v2-e0ccb5427f646b3d14aa.json",
						"kind" : "cache",
						"version" : 
						{
							"major" : 2,
							"minor" : 0
						}
					},
					{
						"jsonFile" : "cmakeFiles-v1-974a3d65760ee1985557.json",
						"kind" : "cmakeFiles",
						"version" : 
						{
							"major" : 1,
							"minor" : 1
						}
					},
					{
						"jsonFile" : "toolchains-v1-1ad29d7dad0522fb55c2.json",
						"kind" : "toolchains",
						"version" : 
						{
							"major" : 1,
							"minor" : 0
						}
					}
				]
			}
		}
	}
}
